cloup/__init__.py
cloup/_commands.py
cloup/_context.py
cloup/_option_groups.py
cloup/_params.py
cloup/_params.pyi
cloup/_sections.py
cloup/_util.py
cloup/_version.py
cloup/py.typed
cloup/styling.py
cloup/types.py
cloup/typing.py
cloup/warnings.py
cloup/constraints/__init__.py
cloup/constraints/_conditional.py
cloup/constraints/_core.py
cloup/constraints/_support.py
cloup/constraints/common.py
cloup/constraints/conditions.py
cloup/constraints/exceptions.py
cloup/formatting/__init__.py
cloup/formatting/_formatter.py
cloup/formatting/_util.py
cloup/formatting/sep.py
cloup-3.0.5.dist-info/LICENSE
cloup-3.0.5.dist-info/METADATA
cloup-3.0.5.dist-info/WHEEL
cloup-3.0.5.dist-info/top_level.txt
cloup-3.0.5.dist-info/RECORD
