Metadata-Version: 2.1
Name: cloup
Version: 3.0.5
Summary: Adds features to Click: option groups, constraints, subcommand sections and help themes.
Home-page: https://github.com/janLuke/cloup
Author: Gianluca Gippetto
Author-email: gianluca.gippetto@gmail.com
License: BSD 3-Clause
Keywords: CLI,click,argument groups,option groups,constraints,help colors,help themes,help styles
Classifier: Intended Audience :: Developers
Classifier: License :: OSI Approved :: BSD License
Classifier: Natural Language :: English
Classifier: Programming Language :: Python :: 3
Classifier: Programming Language :: Python :: 3.7
Classifier: Programming Language :: Python :: 3.8
Classifier: Programming Language :: Python :: 3.9
Classifier: Programming Language :: Python :: 3.10
Classifier: Programming Language :: Python :: 3.11
Requires-Python: >=3.7
License-File: LICENSE
